[
    {
        "id": 1,
        "week": 18,
        "year": 2023,
        "homeTeam": "Arizona Cardinals",
        "awayTeam": "Seattle Seahawks",
        "adjBaseHomeWinPerc": 44,
        "adjBaseAwayWinPerc": 56,
        "basePredictWin": 0,
        "homeMoneyLine": 130,
        "awayMoneyLine": -148,
        "spread": 2.5,
        "total": 47.5,
        "homeGamble": 0,
        "awayGamble": 0,
        "homePayout": 130,
        "awayPayout": 67.57,
        "totalPrediction": 47,
        "overUnderGamble": "-",
        "spreadGamble": "-",
        "spreadPrediction": 6,
        "totalPred": 47,
        "homePrediction": 20,
        "awayPrediction": 26,
        "homeSpreadOdds": -102,
        "awaySpreadOdds": -102,
        "overTotalOdds": -110,
        "underTotalOdds": -110,
        "spreadBetAmount": 0,
        "overUnderBetAmt": 0
    },
    {
        "id": 2,
        "week": 18,
        "year": 2023,
        "homeTeam": "Baltimore Ravens",
        "awayTeam": "Pittsburgh Steelers",
        "adjBaseHomeWinPerc": 70,
        "adjBaseAwayWinPerc": 30,
        "basePredictWin": 1,
        "homeMoneyLine": 130,
        "awayMoneyLine": -155,
        "spread": 3,
        "total": 33.5,
        "homeGamble": 0,
        "awayGamble": 0,
        "homePayout": 130,
        "awayPayout": 64.52,
        "totalPrediction": 47,
        "overUnderGamble": "Under",
        "spreadGamble": "Baltimore Ravens",
        "spreadPrediction": -15,
        "totalPred": 47,
        "homePrediction": 31,
        "awayPrediction": 16,
        "homeSpreadOdds": -115,
        "awaySpreadOdds": -115,
        "overTotalOdds": -110,
        "underTotalOdds": -110,
        "spreadBetAmount": 100,
        "overUnderBetAmt": 100
    },
    {
        "id": 3,
        "week": 18,
        "year": 2023,
        "homeTeam": "Carolina Panthers",
        "awayTeam": "Tampa Bay Buccaneers",
        "adjBaseHomeWinPerc": 25,
        "adjBaseAwayWinPerc": 75,
        "basePredictWin": 0,
        "homeMoneyLine": 190,
        "awayMoneyLine": -230,
        "spread": 4,
        "total": 37,
        "homeGamble": 0,
        "awayGamble": 0,
        "homePayout": 190,
        "awayPayout": 43.48,
        "totalPrediction": 39,
        "overUnderGamble": "-",
        "spreadGamble": "-",
        "spreadPrediction": 7,
        "totalPred": 39,
        "homePrediction": 16,
        "awayPrediction": 23,
        "homeSpreadOdds": -110,
        "awaySpreadOdds": -110,
        "overTotalOdds": -110,
        "underTotalOdds": -110,
        "spreadBetAmount": 0,
        "overUnderBetAmt": 0
    },
    {
        "id": 4,
        "week": 18,
        "year": 2023,
        "homeTeam": "Cincinnati Bengals",
        "awayTeam": "Cleveland Browns",
        "adjBaseHomeWinPerc": 53,
        "adjBaseAwayWinPerc": 47,
        "basePredictWin": 1,
        "homeMoneyLine": -345,
        "awayMoneyLine": 275,
        "spread": -7,
        "total": 37,
        "homeGamble": 0,
        "awayGamble": 0,
        "homePayout": 28.99,
        "awayPayout": 275,
        "totalPrediction": 43,
        "overUnderGamble": "-",
        "spreadGamble": "-",
        "spreadPrediction": 0,
        "totalPred": 43,
        "homePrediction": 22,
        "awayPrediction": 22,
        "homeSpreadOdds": -115,
        "awaySpreadOdds": -115,
        "overTotalOdds": -110,
        "underTotalOdds": -110,
        "spreadBetAmount": 0,
        "overUnderBetAmt": 0
    },
    {
        "id": 5,
        "week": 18,
        "year": 2023,
        "homeTeam": "Detroit Lions",
        "awayTeam": "Minnesota Vikings",
        "adjBaseHomeWinPerc": 74,
        "adjBaseAwayWinPerc": 26,
        "basePredictWin": 1,
        "homeMoneyLine": -185,
        "awayMoneyLine": 154,
        "spread": -3.5,
        "total": 46,
        "homeGamble": 0,
        "awayGamble": 0,
        "homePayout": 54.05,
        "awayPayout": 154,
        "totalPrediction": 45,
        "overUnderGamble": "-",
        "spreadGamble": "-",
        "spreadPrediction": -7,
        "totalPred": 45,
        "homePrediction": 26,
        "awayPrediction": 19,
        "homeSpreadOdds": -108,
        "awaySpreadOdds": -108,
        "overTotalOdds": -110,
        "underTotalOdds": -110,
        "spreadBetAmount": 0,
        "overUnderBetAmt": 0
    },
    {
        "id": 6,
        "week": 18,
        "year": 2023,
        "homeTeam": "Green Bay Packers",
        "awayTeam": "Chicago Bears",
        "adjBaseHomeWinPerc": 61,
        "adjBaseAwayWinPerc": 39,
        "basePredictWin": 1,
        "homeMoneyLine": -155,
        "awayMoneyLine": 130,
        "spread": -3,
        "total": 45.5,
        "homeGamble": 0,
        "awayGamble": 0,
        "homePayout": 64.52,
        "awayPayout": 130,
        "totalPrediction": 46,
        "overUnderGamble": "-",
        "spreadGamble": "-",
        "spreadPrediction": -2,
        "totalPred": 46,
        "homePrediction": 24,
        "awayPrediction": 22,
        "homeSpreadOdds": -105,
        "awaySpreadOdds": -105,
        "overTotalOdds": -110,
        "underTotalOdds": -110,
        "spreadBetAmount": 0,
        "overUnderBetAmt": 0
    },
    {
        "id": 7,
        "week": 18,
        "year": 2023,
        "homeTeam": "Indianapolis Colts",
        "awayTeam": "Houston Texans",
        "adjBaseHomeWinPerc": 58,
        "adjBaseAwayWinPerc": 42,
        "basePredictWin": 1,
        "homeMoneyLine": 100,
        "awayMoneyLine": -120,
        "spread": 1,
        "total": 47.5,
        "homeGamble": 0,
        "awayGamble": 100,
        "homePayout": 100,
        "awayPayout": 83.33,
        "totalPrediction": 44,
        "overUnderGamble": "Under",
        "spreadGamble": "-",
        "spreadPrediction": -3,
        "totalPred": 44,
        "homePrediction": 24,
        "awayPrediction": 20,
        "homeSpreadOdds": -105,
        "awaySpreadOdds": -105,
        "overTotalOdds": -110,
        "underTotalOdds": -110,
        "spreadBetAmount": 0,
        "overUnderBetAmt": 100
    },
    {
        "id": 8,
        "week": 18,
        "year": 2023,
        "homeTeam": "Los Angeles Chargers",
        "awayTeam": "Kansas City Chiefs",
        "adjBaseHomeWinPerc": 32,
        "adjBaseAwayWinPerc": 68,
        "basePredictWin": 0,
        "homeMoneyLine": -185,
        "awayMoneyLine": 154,
        "spread": -3.5,
        "total": 35,
        "homeGamble": 0,
        "awayGamble": 0,
        "homePayout": 54.05,
        "awayPayout": 154,
        "totalPrediction": 45,
        "overUnderGamble": "-",
        "spreadGamble": "-",
        "spreadPrediction": 7,
        "totalPred": 45,
        "homePrediction": 19,
        "awayPrediction": 26,
        "homeSpreadOdds": -110,
        "awaySpreadOdds": -110,
        "overTotalOdds": -110,
        "underTotalOdds": -110,
        "spreadBetAmount": 0,
        "overUnderBetAmt": 0
    },
    {
        "id": 9,
        "week": 18,
        "year": 2023,
        "homeTeam": "Las Vegas Raiders",
        "awayTeam": "Denver Broncos",
        "adjBaseHomeWinPerc": 54,
        "adjBaseAwayWinPerc": 46,
        "basePredictWin": 1,
        "homeMoneyLine": -162,
        "awayMoneyLine": 136,
        "spread": -3,
        "total": 37,
        "homeGamble": 0,
        "awayGamble": 0,
        "homePayout": 61.73,
        "awayPayout": 136,
        "totalPrediction": 41,
        "overUnderGamble": "-",
        "spreadGamble": "-",
        "spreadPrediction": -2,
        "totalPred": 41,
        "homePrediction": 22,
        "awayPrediction": 20,
        "homeSpreadOdds": -108,
        "awaySpreadOdds": -108,
        "overTotalOdds": -110,
        "underTotalOdds": -110,
        "spreadBetAmount": 0,
        "overUnderBetAmt": 0
    },
    {
        "id": 10,
        "week": 18,
        "year": 2023,
        "homeTeam": "Miami Dolphins",
        "awayTeam": "Buffalo Bills",
        "adjBaseHomeWinPerc": 52,
        "adjBaseAwayWinPerc": 48,
        "basePredictWin": 1,
        "homeMoneyLine": 130,
        "awayMoneyLine": -155,
        "spread": 2.5,
        "total": 48,
        "homeGamble": 0,
        "awayGamble": 0,
        "homePayout": 130,
        "awayPayout": 64.52,
        "totalPrediction": 49,
        "overUnderGamble": "-",
        "spreadGamble": "-",
        "spreadPrediction": 0,
        "totalPred": 49,
        "homePrediction": 24,
        "awayPrediction": 24,
        "homeSpreadOdds": 102,
        "awaySpreadOdds": 102,
        "overTotalOdds": -110,
        "underTotalOdds": -110,
        "spreadBetAmount": 0,
        "overUnderBetAmt": 0
    },
    {
        "id": 11,
        "week": 18,
        "year": 2023,
        "homeTeam": "New England Patriots",
        "awayTeam": "New York Jets",
        "adjBaseHomeWinPerc": 41,
        "adjBaseAwayWinPerc": 59,
        "basePredictWin": 0,
        "homeMoneyLine": -130,
        "awayMoneyLine": 110,
        "spread": -2.5,
        "total": 30,
        "homeGamble": 0,
        "awayGamble": 0,
        "homePayout": 76.92,
        "awayPayout": 110,
        "totalPrediction": 38,
        "overUnderGamble": "-",
        "spreadGamble": "-",
        "spreadPrediction": 0,
        "totalPred": 38,
        "homePrediction": 19,
        "awayPrediction": 19,
        "homeSpreadOdds": -102,
        "awaySpreadOdds": -102,
        "overTotalOdds": -110,
        "underTotalOdds": -110,
        "spreadBetAmount": 0,
        "overUnderBetAmt": 0
    },
    {
        "id": 12,
        "week": 18,
        "year": 2023,
        "homeTeam": "New Orleans Saints",
        "awayTeam": "Atlanta Falcons",
        "adjBaseHomeWinPerc": 68,
        "adjBaseAwayWinPerc": 32,
        "basePredictWin": 1,
        "homeMoneyLine": -162,
        "awayMoneyLine": 136,
        "spread": -3,
        "total": 42.5,
        "homeGamble": 0,
        "awayGamble": 0,
        "homePayout": 61.73,
        "awayPayout": 136,
        "totalPrediction": 44,
        "overUnderGamble": "-",
        "spreadGamble": "-",
        "spreadPrediction": -4,
        "totalPred": 44,
        "homePrediction": 24,
        "awayPrediction": 20,
        "homeSpreadOdds": -105,
        "awaySpreadOdds": -105,
        "overTotalOdds": -110,
        "underTotalOdds": -110,
        "spreadBetAmount": 0,
        "overUnderBetAmt": 0
    },
    {
        "id": 13,
        "week": 18,
        "year": 2023,
        "homeTeam": "New York Giants",
        "awayTeam": "Philadelphia Eagles",
        "adjBaseHomeWinPerc": 33,
        "adjBaseAwayWinPerc": 67,
        "basePredictWin": 0,
        "homeMoneyLine": 185,
        "awayMoneyLine": -225,
        "spread": 5,
        "total": 42,
        "homeGamble": 0,
        "awayGamble": 0,
        "homePayout": 185,
        "awayPayout": 44.44,
        "totalPrediction": 47,
        "overUnderGamble": "-",
        "spreadGamble": "-",
        "spreadPrediction": 6,
        "totalPred": 47,
        "homePrediction": 20,
        "awayPrediction": 26,
        "homeSpreadOdds": -115,
        "awaySpreadOdds": -115,
        "overTotalOdds": -110,
        "underTotalOdds": -110,
        "spreadBetAmount": 0,
        "overUnderBetAmt": 0
    },
    {
        "id": 14,
        "week": 18,
        "year": 2023,
        "homeTeam": "San Francisco 49ers",
        "awayTeam": "Los Angeles Rams",
        "adjBaseHomeWinPerc": 79,
        "adjBaseAwayWinPerc": 21,
        "basePredictWin": 1,
        "homeMoneyLine": -205,
        "awayMoneyLine": 170,
        "spread": -4.5,
        "total": 41,
        "homeGamble": 0,
        "awayGamble": 0,
        "homePayout": 48.78,
        "awayPayout": 170,
        "totalPrediction": 49,
        "overUnderGamble": "-",
        "spreadGamble": "-",
        "spreadPrediction": -7,
        "totalPred": 49,
        "homePrediction": 28,
        "awayPrediction": 21,
        "homeSpreadOdds": -110,
        "awaySpreadOdds": -110,
        "overTotalOdds": -110,
        "underTotalOdds": -110,
        "spreadBetAmount": 0,
        "overUnderBetAmt": 0
    },
    {
        "id": 15,
        "week": 18,
        "year": 2023,
        "homeTeam": "Tennessee Titans",
        "awayTeam": "Jacksonville Jaguars",
        "adjBaseHomeWinPerc": 48,
        "adjBaseAwayWinPerc": 52,
        "basePredictWin": 0,
        "homeMoneyLine": 164,
        "awayMoneyLine": -198,
        "spread": 3.5,
        "total": 41,
        "homeGamble": 0,
        "awayGamble": 0,
        "homePayout": 164,
        "awayPayout": 50.51,
        "totalPrediction": 40,
        "overUnderGamble": "-",
        "spreadGamble": "-",
        "spreadPrediction": 4,
        "totalPred": 40,
        "homePrediction": 18,
        "awayPrediction": 22,
        "homeSpreadOdds": -108,
        "awaySpreadOdds": -108,
        "overTotalOdds": -110,
        "underTotalOdds": -110,
        "spreadBetAmount": 0,
        "overUnderBetAmt": 0
    },
    {
        "id": 16,
        "week": 18,
        "year": 2023,
        "homeTeam": "Washington Commanders",
        "awayTeam": "Dallas Cowboys",
        "adjBaseHomeWinPerc": 20,
        "adjBaseAwayWinPerc": 80,
        "basePredictWin": 0,
        "homeMoneyLine": 600,
        "awayMoneyLine": -900,
        "spread": 13,
        "total": 46.5,
        "homeGamble": 0,
        "awayGamble": 0,
        "homePayout": 600,
        "awayPayout": 11.11,
        "totalPrediction": 44,
        "overUnderGamble": "-",
        "spreadGamble": "-",
        "spreadPrediction": 14,
        "totalPred": 44,
        "homePrediction": 15,
        "awayPrediction": 29,
        "homeSpreadOdds": -110,
        "awaySpreadOdds": -110,
        "overTotalOdds": -110,
        "underTotalOdds": -110,
        "spreadBetAmount": 0,
        "overUnderBetAmt": 0
    }
]

